{"leaderboard":[{"name":"Swathi","lillyId":"L047122","score":93,"timeTaken":50,"timeStr":"0:50","timestamp":1776349363827},{"name":"Nasye","lillyId":"3067318","score":150,"timeTaken":238,"timeStr":"3:58","timestamp":1776349517965},{"name":"S","lillyId":"123","score":299,"timeTaken":273,"timeStr":"4:33","timestamp":1776349526415},{"name":"Roshni Shetty","lillyId":"L067320","score":111,"timeTaken":237,"timeStr":"3:57","timestamp":1776349615500},{"name":"Jess","lillyId":"C066643","score":312,"timeTaken":264,"timeStr":"4:24","timestamp":1776349957790},{"name":"Marshy","lillyId":"L005198","score":230,"timeTaken":300,"timeStr":"5:00","timestamp":1776350068471}],"players":["L047122","3067318","123","L067320","C066643","L005198"]}